oban_classifier/__init__.py
oban_classifier/classifier.py
oban_classifier-0.1.86.dist-info/LICENSE.txt
oban_classifier-0.1.86.dist-info/METADATA
oban_classifier-0.1.86.dist-info/WHEEL
oban_classifier-0.1.86.dist-info/top_level.txt
oban_classifier-0.1.86.dist-info/RECORD
