Metadata-Version: 2.1
Name: oban_classifier
Version: 0.1.86
Summary: Oban Classifier: A Skorch-based flexible neural network for binary and multiclass classification
Author: Dr. Volkan OBAN
Author-email: volkanobn@gmail.com
Classifier: Development Status :: 4 - Beta
Classifier: Intended Audience :: Developers
Classifier: Programming Language :: Python :: 3.8
Classifier: Programming Language :: Python :: 3.9
Classifier: Topic :: Scientific/Engineering :: Artificial Intelligence
Requires-Python: >=3.8
License-File: LICENSE.txt
Requires-Dist: numpy
Requires-Dist: pandas
Requires-Dist: scikit-learn
Requires-Dist: skorch
Requires-Dist: torch
